funcserver/__init__.py
funcserver/funcserver.py
funcserver/static/css/bootstrap-theme.css
funcserver/static/css/bootstrap-theme.min.css
funcserver/static/css/bootstrap.css
funcserver/static/css/bootstrap.min.css
funcserver/static/css/jquery.terminal.css
funcserver/static/css/main.css
funcserver/static/fonts/glyphicons-halflings-regular.eot
funcserver/static/fonts/glyphicons-halflings-regular.svg
funcserver/static/fonts/glyphicons-halflings-regular.ttf
funcserver/static/fonts/glyphicons-halflings-regular.woff
funcserver/static/img/bg.png
funcserver/static/img/logo16x16.png
funcserver/static/js/bootstrap.min.js
funcserver/static/js/html5shiv.js
funcserver/static/js/jquery-1.9.1.min.js
funcserver/static/js/jquery.mousewheel.js
funcserver/static/js/jquery.terminal-0.8.7.min.js
funcserver/static/js/respond.min.js
funcserver/static/js/underscore-min.js
funcserver/static/js/utils.js
funcserver/templates/base.html
funcserver/templates/console.html
funcserver/templates/home.html
funcserver/templates/logs.html
funcserver-0.2.17.dist-info/DESCRIPTION.rst
funcserver-0.2.17.dist-info/METADATA
funcserver-0.2.17.dist-info/RECORD
funcserver-0.2.17.dist-info/WHEEL
funcserver-0.2.17.dist-info/metadata.json
funcserver-0.2.17.dist-info/top_level.txt
