Metadata-Version: 2.0
Name: funcserver
Version: 0.2.17
Summary: Simple and opiniated way to build APIs in Python
Home-page: https://github.com/deep-compute/funcserver
Author: Deep Compute, LLC
Author-email: contact@deepcompute.com
License: MIT License
Download-URL: https://github.com/deep-compute/funcserver/tarball/0.2.17
Keywords: funcserver
Platform: UNKNOWN
Classifier: Programming Language :: Python :: 2.7
Classifier: Environment :: Console
Classifier: Intended Audience :: Developers
Classifier: License :: OSI Approved :: MIT License
Requires-Dist: basescript (>=0.1.6)
Requires-Dist: msgpack-python
Requires-Dist: requests
Requires-Dist: statsd
Requires-Dist: tornado
